jatarag/__init__.py
jatarag/agent.py
jatarag/db/__init__.py
jatarag/db/filesysdb.py
jatarag/db/flexible_database_example.py
jatarag/db/interface.py
jatarag/demo.py
jatarag/embedder/__init__.py
jatarag/embedder/ada.py
jatarag/embedder/interface.py
jatarag/extractor/__init__.py
jatarag/extractor/interface.py
jatarag/extractor/nougat.py
jatarag/librarian.py
jatarag/utils.py
jatarag-0.1.8.dist-info/LICENSE
jatarag-0.1.8.dist-info/METADATA
jatarag-0.1.8.dist-info/WHEEL
jatarag-0.1.8.dist-info/RECORD
