Metadata-Version: 2.1
Name: jatarag
Version: 0.1.8
Summary: Retrieval Augmented Generation (RAG) starter library
Home-page: https://github.com/jataware/jatarag
License: MIT
Author: David Samson
Author-email: dsamson@jataware.com
Requires-Python: >=3.8
Classifier: License :: OSI Approved :: MIT License
Classifier: Programming Language :: Python :: 3
Classifier: Programming Language :: Python :: 3.8
Classifier: Programming Language :: Python :: 3.9
Classifier: Programming Language :: Python :: 3.10
Classifier: Programming Language :: Python :: 3.11
Classifier: Programming Language :: Python :: 3.12
Requires-Dist: easyrepl (>=0.1.3,<0.2.0)
Requires-Dist: fuzzywuzzy (>=0.18.0,<0.19.0)
Requires-Dist: nougat-ocr (>=0.1.17,<0.2.0)
Requires-Dist: numpy (>=1.24)
Requires-Dist: openai[embeddings] (>=1.35.6,<2.0.0)
Requires-Dist: pypdf (>=4.2.0,<5.0.0)
Requires-Dist: tiktoken (>=0.7.0,<0.8.0)
Requires-Dist: tqdm (>=4.66.4,<5.0.0)
